xfntr/__init__.py
xfntr/command_line.py
xfntr/fit_ref.py
xfntr/flu_geometry_routines.py
xfntr/flu_routines_new.py
xfntr/fluorescence.py
xfntr/main.py
xfntr/mainwindow.py
xfntr/mplwidget.py
xfntr/GUI/err1.ui
xfntr/GUI/err2.ui
xfntr/GUI/err3.ui
xfntr/GUI/err4.ui
xfntr/GUI/flupara.ui
xfntr/GUI/formfactorDialog.ui
xfntr/GUI/gixsyspara.ui
xfntr/GUI/mainwindow.ui
xfntr/GUI/plotscale.ui
xfntr/GUI/ref_multiFit_par.ui
xfntr/GUI/refpara.ui
xfntr/GUI/refsave.ui
xfntr/GUI/refsyspara.ui
xfntr/GUI/rodpara.ui
xfntr/images/TaiChi.icns
xfntr/test/sample5_1mMEuHDEHP_water_1_fit.txt
xfntr/test/sample5_1mMEuHDEHP_water_1_flu.txt
xfntr/test/sample5_1mMEuHDEHP_water_1_par.txt
xfntr/test/sh_sample03_318_50mMEu(NO3)3_s1h0.2_qz0.0015_par.txt
xfntr_win-0.3.1.dist-info/LICENSE
xfntr_win-0.3.1.dist-info/METADATA
xfntr_win-0.3.1.dist-info/WHEEL
xfntr_win-0.3.1.dist-info/entry_points.txt
xfntr_win-0.3.1.dist-info/top_level.txt
xfntr_win-0.3.1.dist-info/RECORD
